{
    "bingoId": "istj",
    "title": "ISTJ宾果",
    "creator": "请手动填写",
    "description": "五个连成一条线，你就是一只蓝老头",
    "gridSize": {
        "rows": 5,
        "cols": 5
    },
    "gridContent": [
        [
            {
                "text": "顶配打工人",
                "type": "standard"
            },
            {
                "text": "契约精神",
                "type": "standard"
            },
            {
                "text": "可以接受剧透",
                "type": "standard"
            },
            {
                "text": "喜欢的菜会反复点",
                "type": "standard"
            },
            {
                "text": "比水还淡",
                "type": "standard"
            }
        ],
        [
            {
                "text": "遵守时间讨厌迟到",
                "type": "standard"
            },
            {
                "text": "慕强",
                "type": "standard"
            },
            {
                "text": "说话从不拐弯",
                "type": "standard"
            },
            {
                "text": "厌恶风险",
                "type": "standard"
            },
            {
                "text": "不懂得如何安慰别人",
                "type": "standard"
            }
        ],
        [
            {
                "text": "用实际行动表达爱",
                "type": "standard"
            },
            {
                "text": "低攻高防",
                "type": "standard"
            },
            {
                "text": "谁也别打乱我的计划",
                "type": "standard"
            },
            {
                "text": "无病呻吟有什么用啊",
                "type": "standard"
            },
            {
                "text": "谁影响我我就放弃谁",
                "type": "standard"
            }
        ],
        [
            {
                "text": "道德标准很高",
                "type": "standard"
            },
            {
                "text": "其实内心戏很足",
                "type": "standard"
            },
            {
                "text": "喜欢极简主义设计",
                "type": "standard"
            },
            {
                "text": "睡前忍不住想明天的计划",
                "type": "standard"
            },
            {
                "text": "大量时间需要独处",
                "type": "standard"
            }
        ],
        [
            {
                "text": "没什么情绪起伏",
                "type": "standard"
            },
            {
                "text": "想的多讲的少",
                "type": "standard"
            },
            {
                "text": "手机常年开静音",
                "type": "standard"
            },
            {
                "text": "喜欢上网冲浪但懒得点赞",
                "type": "standard"
            },
            {
                "text": "完美主义",
                "type": "standard"
            }
        ]
    ],
    "category": "待分类",
    "tags": [],
    "createdAt": ""
}